quick_rest/__init__.py
quick_rest/auth.py
quick_rest/client.py
quick_rest/exceptions.py
quick_rest/resources.py
quick_rest-0.1.9.dist-info/LICENSE
quick_rest-0.1.9.dist-info/METADATA
quick_rest-0.1.9.dist-info/WHEEL
quick_rest-0.1.9.dist-info/top_level.txt
quick_rest-0.1.9.dist-info/RECORD
