Metadata-Version: 2.1
Name: quick-rest
Version: 0.1.9
Summary: A versatile wrapper for REST APIs.
Home-page: https://github.com/michaeleveringham/quick_rest
Author: Michael Everingham
Author-email: lamerlink@live.com
Classifier: Development Status :: 4 - Beta
Classifier: License :: OSI Approved :: MIT License
Classifier: Programming Language :: Python :: 3.7
Classifier: Operating System :: OS Independent
Classifier: Typing :: Typed
Requires-Python: >=3.7
License-File: LICENSE
Requires-Dist: requests (>=2.26.0)
